{
  "url": "https://www.oreillyauto.com/",
  "extractedAt": "2025-10-16T10:41:41.798Z",
  "content": {
    "favicon": [],
    "title": "Access Denied",
    "metaDescription": "",
    "content": "# Access Denied\n You don't have permission to access \"http://www.oreillyauto.com/?\" on this server. Reference #18.9b071002.1760611301.1e2774b7 \nhttps://errors.edgesuite.net/18.9b071002.1760611301.1e2774b7",
    "truncated": false,
    "fullContentLength": 204,
    "headings": [
      {
        "level": 1,
        "text": "Access Denied"
      }
    ],
    "links": [],
    "images": [],
    "timestamp": 1760611301404,
    "url": "https://www.oreillyauto.com/?automation=true?automation=true&wait-for-init-args=true"
  }
}